{
  "sip": 16,
  "name": "Stacks Whales #1407",
  "properties": {
    "collection": "Stacks Whales"
  },
  "description": "Whale NFTs on the Stack blockchain are a captivating way to own and display artwork of majestic sea creatures.",
  "size": "10000",
  "price": "1",
  "external_url": "",
  "dna": "2891ba0ff26fdb00816f35d5cef60f00b25551bf",
  "edition": 1407,
  "date": 1678008598922,
  "attributes": [
    {
      "trait": "BACKGROUND",
      "value": "CYAN"
    },
    {
      "trait": "BASE",
      "value": "WHALEY ORANGE"
    },
    {
      "trait": "EYE ACCESSORY",
      "value": "NONE"
    },
    {
      "trait": "HEADGEAR",
      "value": "AMIGO"
    },
    {
      "trait": "MOUTH ACCESSORY",
      "value": "VAPE"
    }
  ],
  "asset_type": "image/png",
  "image": "ipfs://ipfs/QmYSyAWEo9Jv46QhVvzsDmZt7sPCHKE5ChjcHf3MPY7Y1E/images/1407.png"
}