{
  "sip": 16,
  "name": "Stacks Whales #1572",
  "properties": {
    "collection": "Stacks Whales"
  },
  "description": "Whale NFTs on the Stack blockchain are a captivating way to own and display artwork of majestic sea creatures.",
  "size": "10000",
  "price": "1",
  "external_url": "",
  "dna": "117911bba171c815db6e8bfb174cf55c6cbd02e1",
  "edition": 1572,
  "date": 1678009051135,
  "attributes": [
    {
      "trait": "BACKGROUND",
      "value": "RED"
    },
    {
      "trait": "BASE",
      "value": "WHALEY BABYBLUE"
    },
    {
      "trait": "EYE ACCESSORY",
      "value": "BLUE EYE SHADOW"
    },
    {
      "trait": "HEADGEAR",
      "value": "PURPLE BEATS"
    },
    {
      "trait": "MOUTH ACCESSORY",
      "value": "NONE"
    }
  ],
  "asset_type": "image/png",
  "image": "ipfs://ipfs/QmYSyAWEo9Jv46QhVvzsDmZt7sPCHKE5ChjcHf3MPY7Y1E/images/1572.png"
}