{
  "sip": 16,
  "name": "Stacks Whales #1803",
  "properties": {
    "collection": "Stacks Whales"
  },
  "description": "Whale NFTs on the Stack blockchain are a captivating way to own and display artwork of majestic sea creatures.",
  "size": "10000",
  "price": "1",
  "external_url": "",
  "dna": "bcc5e3df4037c359321607b2b396dc30f2db674e",
  "edition": 1803,
  "date": 1678009139818,
  "attributes": [
    {
      "trait": "BACKGROUND",
      "value": "GREEN"
    },
    {
      "trait": "BASE",
      "value": "WHALEY LILA"
    },
    {
      "trait": "EYE ACCESSORY",
      "value": "NONE"
    },
    {
      "trait": "HEADGEAR",
      "value": "FEDORA RED"
    },
    {
      "trait": "MOUTH ACCESSORY",
      "value": "NONE"
    }
  ],
  "asset_type": "image/png",
  "image": "ipfs://ipfs/QmYSyAWEo9Jv46QhVvzsDmZt7sPCHKE5ChjcHf3MPY7Y1E/images/1803.png"
}