{
  "sip": 16,
  "name": "Stacks Whales #1929",
  "properties": {
    "collection": "Stacks Whales"
  },
  "description": "Whale NFTs on the Stack blockchain are a captivating way to own and display artwork of majestic sea creatures.",
  "size": "10000",
  "price": "1",
  "external_url": "",
  "dna": "8ea614e6adf30e294a19e5c31c02b4cb385c2ff6",
  "edition": 1929,
  "date": 1678009094221,
  "attributes": [
    {
      "trait": "BACKGROUND",
      "value": "PEACH"
    },
    {
      "trait": "BASE",
      "value": "WHALEY BABYBLUE"
    },
    {
      "trait": "EYE ACCESSORY",
      "value": "PURPLE EYE SHADOW"
    },
    {
      "trait": "HEADGEAR",
      "value": "ORANGE CAP"
    },
    {
      "trait": "MOUTH ACCESSORY",
      "value": "PIPE"
    }
  ],
  "asset_type": "image/png",
  "image": "ipfs://ipfs/QmYSyAWEo9Jv46QhVvzsDmZt7sPCHKE5ChjcHf3MPY7Y1E/images/1929.png"
}