{
  "sip": 16,
  "name": "Stacks Whales #2066",
  "properties": {
    "collection": "Stacks Whales"
  },
  "description": "Whale NFTs on the Stack blockchain are a captivating way to own and display artwork of majestic sea creatures.",
  "size": "10000",
  "price": "1",
  "external_url": "",
  "dna": "9e65277ea5abeacd1baa4d9866f2e23fb1e1672b",
  "edition": 2066,
  "date": 1678008778929,
  "attributes": [
    {
      "trait": "BACKGROUND",
      "value": "ORANGE"
    },
    {
      "trait": "BASE",
      "value": "WHALEY BLACK"
    },
    {
      "trait": "EYE ACCESSORY",
      "value": "BLUE EYE SHADOW"
    },
    {
      "trait": "HEADGEAR",
      "value": "HIGH HAT"
    },
    {
      "trait": "MOUTH ACCESSORY",
      "value": "VAPE"
    }
  ],
  "asset_type": "image/png",
  "image": "ipfs://ipfs/QmYSyAWEo9Jv46QhVvzsDmZt7sPCHKE5ChjcHf3MPY7Y1E/images/2066.png"
}