{
  "sip": 16,
  "name": "Stacks Whales #2338",
  "properties": {
    "collection": "Stacks Whales"
  },
  "description": "Whale NFTs on the Stack blockchain are a captivating way to own and display artwork of majestic sea creatures.",
  "size": "10000",
  "price": "1",
  "external_url": "",
  "dna": "dda0015654a8837d1c0af39dcee94789865423bf",
  "edition": 2338,
  "date": 1678009090394,
  "attributes": [
    {
      "trait": "BACKGROUND",
      "value": "CYAN"
    },
    {
      "trait": "BASE",
      "value": "WHALEY BLUE"
    },
    {
      "trait": "EYE ACCESSORY",
      "value": "ANGRY"
    },
    {
      "trait": "HEADGEAR",
      "value": "GREEN CAP"
    },
    {
      "trait": "MOUTH ACCESSORY",
      "value": "BUBBLEGUM"
    }
  ],
  "asset_type": "image/png",
  "image": "ipfs://ipfs/QmYSyAWEo9Jv46QhVvzsDmZt7sPCHKE5ChjcHf3MPY7Y1E/images/2338.png"
}