{
  "sip": 16,
  "name": "Stacks Whales #2372",
  "properties": {
    "collection": "Stacks Whales"
  },
  "description": "Whale NFTs on the Stack blockchain are a captivating way to own and display artwork of majestic sea creatures.",
  "size": "10000",
  "price": "1",
  "external_url": "",
  "dna": "92e5107d3622732a20ad754d65e22d7859bd6d4d",
  "edition": 2372,
  "date": 1678008687003,
  "attributes": [
    {
      "trait": "BACKGROUND",
      "value": "WHITE"
    },
    {
      "trait": "BASE",
      "value": "WHALEY BABYBLUE"
    },
    {
      "trait": "EYE ACCESSORY",
      "value": "CLOWN EYE"
    },
    {
      "trait": "HEADGEAR",
      "value": "GREEN HEADBAND"
    },
    {
      "trait": "MOUTH ACCESSORY",
      "value": "NONE"
    }
  ],
  "asset_type": "image/png",
  "image": "ipfs://ipfs/QmYSyAWEo9Jv46QhVvzsDmZt7sPCHKE5ChjcHf3MPY7Y1E/images/2372.png"
}