{
  "sip": 16,
  "name": "Stacks Whales #2402",
  "properties": {
    "collection": "Stacks Whales"
  },
  "description": "Whale NFTs on the Stack blockchain are a captivating way to own and display artwork of majestic sea creatures.",
  "size": "10000",
  "price": "1",
  "external_url": "",
  "dna": "ac4b41a7cd7307e27307a25272d9c6c65352f52f",
  "edition": 2402,
  "date": 1678009079250,
  "attributes": [
    {
      "trait": "BACKGROUND",
      "value": "ORANGE"
    },
    {
      "trait": "BASE",
      "value": "WHALEY BLACK"
    },
    {
      "trait": "EYE ACCESSORY",
      "value": "BLUE EYE SHADOW"
    },
    {
      "trait": "HEADGEAR",
      "value": "BLUE HEADBAND"
    },
    {
      "trait": "MOUTH ACCESSORY",
      "value": "PIPE"
    }
  ],
  "asset_type": "image/png",
  "image": "ipfs://ipfs/QmYSyAWEo9Jv46QhVvzsDmZt7sPCHKE5ChjcHf3MPY7Y1E/images/2402.png"
}