{
  "sip": 16,
  "name": "Stacks Whales #31",
  "properties": {
    "collection": "Stacks Whales"
  },
  "description": "Whale NFTs on the Stack blockchain are a captivating way to own and display artwork of majestic sea creatures.",
  "size": "10000",
  "price": "1",
  "external_url": "",
  "dna": "94a0dad85d1d6ba48f2b3491d1e7d30b9bd3b159",
  "edition": 31,
  "date": 1678008439460,
  "attributes": [
    {
      "trait": "BACKGROUND",
      "value": "BABY BLUE"
    },
    {
      "trait": "BASE",
      "value": "WHALEY ZOMBIE"
    },
    {
      "trait": "EYE ACCESSORY",
      "value": "GOLD EYE SHADOW"
    },
    {
      "trait": "HEADGEAR",
      "value": "RED BEATS"
    },
    {
      "trait": "MOUTH ACCESSORY",
      "value": "NONE"
    }
  ],
  "asset_type": "image/png",
  "image": "ipfs://ipfs/QmYSyAWEo9Jv46QhVvzsDmZt7sPCHKE5ChjcHf3MPY7Y1E/images/31.png"
}