{
  "sip": 16,
  "name": "Stacks Whales #3123",
  "properties": {
    "collection": "Stacks Whales"
  },
  "description": "Whale NFTs on the Stack blockchain are a captivating way to own and display artwork of majestic sea creatures.",
  "size": "10000",
  "price": "1",
  "external_url": "",
  "dna": "a3a78bca785bffe1820014596ac1f1f235e7ee9a",
  "edition": 3123,
  "date": 1678008536208,
  "attributes": [
    {
      "trait": "BACKGROUND",
      "value": "BABY BLUE"
    },
    {
      "trait": "BASE",
      "value": "WHALEY RED"
    },
    {
      "trait": "EYE ACCESSORY",
      "value": "BLUE EYE SHADOW"
    },
    {
      "trait": "HEADGEAR",
      "value": "FEDORA BROWN"
    },
    {
      "trait": "MOUTH ACCESSORY",
      "value": "BUBBLEGUM"
    }
  ],
  "asset_type": "image/png",
  "image": "ipfs://ipfs/QmYSyAWEo9Jv46QhVvzsDmZt7sPCHKE5ChjcHf3MPY7Y1E/images/3123.png"
}