{
  "sip": 16,
  "name": "Stacks Whales #3126",
  "properties": {
    "collection": "Stacks Whales"
  },
  "description": "Whale NFTs on the Stack blockchain are a captivating way to own and display artwork of majestic sea creatures.",
  "size": "10000",
  "price": "1",
  "external_url": "",
  "dna": "5c48c398ee8b9269fd6f397cbeae086e5d0795df",
  "edition": 3126,
  "date": 1678008862347,
  "attributes": [
    {
      "trait": "BACKGROUND",
      "value": "PURPLE"
    },
    {
      "trait": "BASE",
      "value": "WHALEY ORANGE"
    },
    {
      "trait": "EYE ACCESSORY",
      "value": "NONE"
    },
    {
      "trait": "HEADGEAR",
      "value": "RED HEADBAND"
    },
    {
      "trait": "MOUTH ACCESSORY",
      "value": "BUBBLEGUM"
    }
  ],
  "asset_type": "image/png",
  "image": "ipfs://ipfs/QmYSyAWEo9Jv46QhVvzsDmZt7sPCHKE5ChjcHf3MPY7Y1E/images/3126.png"
}