{
  "sip": 16,
  "name": "Stacks Whales #3594",
  "properties": {
    "collection": "Stacks Whales"
  },
  "description": "Whale NFTs on the Stack blockchain are a captivating way to own and display artwork of majestic sea creatures.",
  "size": "10000",
  "price": "1",
  "external_url": "",
  "dna": "93c5b45f88593590aeb85532bcd40c2c502b8b37",
  "edition": 3594,
  "date": 1678008961106,
  "attributes": [
    {
      "trait": "BACKGROUND",
      "value": "WHITE"
    },
    {
      "trait": "BASE",
      "value": "WHALEY BLUE"
    },
    {
      "trait": "EYE ACCESSORY",
      "value": "LASER EYE"
    },
    {
      "trait": "HEADGEAR",
      "value": "RED HEADBAND"
    },
    {
      "trait": "MOUTH ACCESSORY",
      "value": "VAPE"
    }
  ],
  "asset_type": "image/png",
  "image": "ipfs://ipfs/QmYSyAWEo9Jv46QhVvzsDmZt7sPCHKE5ChjcHf3MPY7Y1E/images/3594.png"
}