{
  "sip": 16,
  "name": "Stacks Whales #3721",
  "properties": {
    "collection": "Stacks Whales"
  },
  "description": "Whale NFTs on the Stack blockchain are a captivating way to own and display artwork of majestic sea creatures.",
  "size": "10000",
  "price": "1",
  "external_url": "",
  "dna": "76de62a8612ae765a00e464b76602656807f0d7c",
  "edition": 3721,
  "date": 1678009003488,
  "attributes": [
    {
      "trait": "BACKGROUND",
      "value": "GRAY"
    },
    {
      "trait": "BASE",
      "value": "WHALEY VIOLET"
    },
    {
      "trait": "EYE ACCESSORY",
      "value": "NONE"
    },
    {
      "trait": "HEADGEAR",
      "value": "MUSIC "
    },
    {
      "trait": "MOUTH ACCESSORY",
      "value": "NONE"
    }
  ],
  "asset_type": "image/png",
  "image": "ipfs://ipfs/QmYSyAWEo9Jv46QhVvzsDmZt7sPCHKE5ChjcHf3MPY7Y1E/images/3721.png"
}