{
  "sip": 16,
  "name": "Stacks Whales #3834",
  "properties": {
    "collection": "Stacks Whales"
  },
  "description": "Whale NFTs on the Stack blockchain are a captivating way to own and display artwork of majestic sea creatures.",
  "size": "10000",
  "price": "1",
  "external_url": "",
  "dna": "e4f5317b3cc45f16ab6de9d546df4dd1ca0c06e9",
  "edition": 3834,
  "date": 1678008896076,
  "attributes": [
    {
      "trait": "BACKGROUND",
      "value": "BLUE"
    },
    {
      "trait": "BASE",
      "value": "WHALEY BLUE"
    },
    {
      "trait": "EYE ACCESSORY",
      "value": "PURPLE EYE SHADOW"
    },
    {
      "trait": "HEADGEAR",
      "value": "MONEY BEATS"
    },
    {
      "trait": "MOUTH ACCESSORY",
      "value": "NONE"
    }
  ],
  "asset_type": "image/png",
  "image": "ipfs://ipfs/QmYSyAWEo9Jv46QhVvzsDmZt7sPCHKE5ChjcHf3MPY7Y1E/images/3834.png"
}