{
  "sip": 16,
  "name": "Stacks Whales #3876",
  "properties": {
    "collection": "Stacks Whales"
  },
  "description": "Whale NFTs on the Stack blockchain are a captivating way to own and display artwork of majestic sea creatures.",
  "size": "10000",
  "price": "1",
  "external_url": "",
  "dna": "fa10e2b6febe30d11d32a8a0b26c1044b2ca42df",
  "edition": 3876,
  "date": 1678008925223,
  "attributes": [
    {
      "trait": "BACKGROUND",
      "value": "PEACH"
    },
    {
      "trait": "BASE",
      "value": "WHALEY BABYBLUE"
    },
    {
      "trait": "EYE ACCESSORY",
      "value": "PURPLE EYE SHADOW"
    },
    {
      "trait": "HEADGEAR",
      "value": "PURPLE BEATS"
    },
    {
      "trait": "MOUTH ACCESSORY",
      "value": "NONE"
    }
  ],
  "asset_type": "image/png",
  "image": "ipfs://ipfs/QmYSyAWEo9Jv46QhVvzsDmZt7sPCHKE5ChjcHf3MPY7Y1E/images/3876.png"
}