{
  "sip": 16,
  "name": "Stacks Whales #3901",
  "properties": {
    "collection": "Stacks Whales"
  },
  "description": "Whale NFTs on the Stack blockchain are a captivating way to own and display artwork of majestic sea creatures.",
  "size": "10000",
  "price": "1",
  "external_url": "",
  "dna": "bf289b2b5d13533483dc02b5be304c03628d2c58",
  "edition": 3901,
  "date": 1678008692368,
  "attributes": [
    {
      "trait": "BACKGROUND",
      "value": "GRAY"
    },
    {
      "trait": "BASE",
      "value": "WHALEY ORANGE"
    },
    {
      "trait": "EYE ACCESSORY",
      "value": "GREEN EYE SHADOW"
    },
    {
      "trait": "HEADGEAR",
      "value": "NONE"
    },
    {
      "trait": "MOUTH ACCESSORY",
      "value": "VAPE"
    }
  ],
  "asset_type": "image/png",
  "image": "ipfs://ipfs/QmYSyAWEo9Jv46QhVvzsDmZt7sPCHKE5ChjcHf3MPY7Y1E/images/3901.png"
}