{
  "sip": 16,
  "name": "Stacks Whales #396",
  "properties": {
    "collection": "Stacks Whales"
  },
  "description": "Whale NFTs on the Stack blockchain are a captivating way to own and display artwork of majestic sea creatures.",
  "size": "10000",
  "price": "1",
  "external_url": "",
  "dna": "5e3f57e6c9b110d0fc61300eb2ccac0a0d1ef44f",
  "edition": 396,
  "date": 1678008759449,
  "attributes": [
    {
      "trait": "BACKGROUND",
      "value": "PINK"
    },
    {
      "trait": "BASE",
      "value": "WHALEY BABYBLUE"
    },
    {
      "trait": "EYE ACCESSORY",
      "value": "NONE"
    },
    {
      "trait": "HEADGEAR",
      "value": "HIGH HAT"
    },
    {
      "trait": "MOUTH ACCESSORY",
      "value": "NONE"
    }
  ],
  "asset_type": "image/png",
  "image": "ipfs://ipfs/QmYSyAWEo9Jv46QhVvzsDmZt7sPCHKE5ChjcHf3MPY7Y1E/images/396.png"
}