{
  "sip": 16,
  "name": "Stacks Whales #3978",
  "properties": {
    "collection": "Stacks Whales"
  },
  "description": "Whale NFTs on the Stack blockchain are a captivating way to own and display artwork of majestic sea creatures.",
  "size": "10000",
  "price": "1",
  "external_url": "",
  "dna": "f3baa423aa3117827a0fd2cac8edebf709bc145c",
  "edition": 3978,
  "date": 1678008802597,
  "attributes": [
    {
      "trait": "BACKGROUND",
      "value": "WHITE"
    },
    {
      "trait": "BASE",
      "value": "WHALEY LILA"
    },
    {
      "trait": "EYE ACCESSORY",
      "value": "NONE"
    },
    {
      "trait": "HEADGEAR",
      "value": "ORANGE CAP"
    },
    {
      "trait": "MOUTH ACCESSORY",
      "value": "PIPE"
    }
  ],
  "asset_type": "image/png",
  "image": "ipfs://ipfs/QmYSyAWEo9Jv46QhVvzsDmZt7sPCHKE5ChjcHf3MPY7Y1E/images/3978.png"
}