{
  "sip": 16,
  "name": "Stacks Whales #404",
  "properties": {
    "collection": "Stacks Whales"
  },
  "description": "Whale NFTs on the Stack blockchain are a captivating way to own and display artwork of majestic sea creatures.",
  "size": "10000",
  "price": "1",
  "external_url": "",
  "dna": "932873542fd963a45e1feb15e52304fa96a43eb7",
  "edition": 404,
  "date": 1678009007382,
  "attributes": [
    {
      "trait": "BACKGROUND",
      "value": "RED"
    },
    {
      "trait": "BASE",
      "value": "WHALEY BLACK"
    },
    {
      "trait": "EYE ACCESSORY",
      "value": "CLOWN EYE"
    },
    {
      "trait": "HEADGEAR",
      "value": "YELLOW CAP"
    },
    {
      "trait": "MOUTH ACCESSORY",
      "value": "NONE"
    }
  ],
  "asset_type": "image/png",
  "image": "ipfs://ipfs/QmYSyAWEo9Jv46QhVvzsDmZt7sPCHKE5ChjcHf3MPY7Y1E/images/404.png"
}