{
  "sip": 16,
  "name": "Stacks Whales #467",
  "properties": {
    "collection": "Stacks Whales"
  },
  "description": "Whale NFTs on the Stack blockchain are a captivating way to own and display artwork of majestic sea creatures.",
  "size": "10000",
  "price": "1",
  "external_url": "",
  "dna": "393ac4d329e06e7d67d7c6222856469ae5193c49",
  "edition": 467,
  "date": 1678009009341,
  "attributes": [
    {
      "trait": "BACKGROUND",
      "value": "PEACH"
    },
    {
      "trait": "BASE",
      "value": "WHALEY ORANGE"
    },
    {
      "trait": "EYE ACCESSORY",
      "value": "PURPLE EYE SHADOW"
    },
    {
      "trait": "HEADGEAR",
      "value": "RED CAP"
    },
    {
      "trait": "MOUTH ACCESSORY",
      "value": "NONE"
    }
  ],
  "asset_type": "image/png",
  "image": "ipfs://ipfs/QmYSyAWEo9Jv46QhVvzsDmZt7sPCHKE5ChjcHf3MPY7Y1E/images/467.png"
}