{
  "sip": 16,
  "name": "Stacks Whales #5236",
  "properties": {
    "collection": "Stacks Whales"
  },
  "description": "Whale NFTs on the Stack blockchain are a captivating way to own and display artwork of majestic sea creatures.",
  "size": "10000",
  "price": "1",
  "external_url": "",
  "dna": "4049fba30fdb33947ac65cedbdbe4b0d2b2eb637",
  "edition": 5236,
  "date": 1678008473612,
  "attributes": [
    {
      "trait": "BACKGROUND",
      "value": "BLUE"
    },
    {
      "trait": "BASE",
      "value": "WHALEY GREEN"
    },
    {
      "trait": "EYE ACCESSORY",
      "value": "CLOWN EYE"
    },
    {
      "trait": "HEADGEAR",
      "value": "GREEN CAP"
    },
    {
      "trait": "MOUTH ACCESSORY",
      "value": "NONE"
    }
  ],
  "asset_type": "image/png",
  "image": "ipfs://ipfs/QmYSyAWEo9Jv46QhVvzsDmZt7sPCHKE5ChjcHf3MPY7Y1E/images/5236.png"
}