{
  "sip": 16,
  "name": "Stacks Whales #5667",
  "properties": {
    "collection": "Stacks Whales"
  },
  "description": "Whale NFTs on the Stack blockchain are a captivating way to own and display artwork of majestic sea creatures.",
  "size": "10000",
  "price": "1",
  "external_url": "",
  "dna": "e2f5a02cd8e2c6a2935a043e3b7112a729225078",
  "edition": 5667,
  "date": 1678009123836,
  "attributes": [
    {
      "trait": "BACKGROUND",
      "value": "PEACH"
    },
    {
      "trait": "BASE",
      "value": "WHALEY BABYBLUE"
    },
    {
      "trait": "EYE ACCESSORY",
      "value": "PURPLE EYE SHADOW"
    },
    {
      "trait": "HEADGEAR",
      "value": "YELLOW CAP"
    },
    {
      "trait": "MOUTH ACCESSORY",
      "value": "NONE"
    }
  ],
  "asset_type": "image/png",
  "image": "ipfs://ipfs/QmYSyAWEo9Jv46QhVvzsDmZt7sPCHKE5ChjcHf3MPY7Y1E/images/5667.png"
}