{
  "sip": 16,
  "name": "Stacks Whales #601",
  "properties": {
    "collection": "Stacks Whales"
  },
  "description": "Whale NFTs on the Stack blockchain are a captivating way to own and display artwork of majestic sea creatures.",
  "size": "10000",
  "price": "1",
  "external_url": "",
  "dna": "4a36ebc76178891a260b0356fe7817f3bfb60ace",
  "edition": 601,
  "date": 1678008458365,
  "attributes": [
    {
      "trait": "BACKGROUND",
      "value": "CYAN"
    },
    {
      "trait": "BASE",
      "value": "WHALEY BLACK"
    },
    {
      "trait": "EYE ACCESSORY",
      "value": "BLUE EYE SHADOW"
    },
    {
      "trait": "HEADGEAR",
      "value": "YELLOW CAP"
    },
    {
      "trait": "MOUTH ACCESSORY",
      "value": "NONE"
    }
  ],
  "asset_type": "image/png",
  "image": "ipfs://ipfs/QmYSyAWEo9Jv46QhVvzsDmZt7sPCHKE5ChjcHf3MPY7Y1E/images/601.png"
}