{
  "sip": 16,
  "name": "Stacks Whales #6113",
  "properties": {
    "collection": "Stacks Whales"
  },
  "description": "Whale NFTs on the Stack blockchain are a captivating way to own and display artwork of majestic sea creatures.",
  "size": "10000",
  "price": "1",
  "external_url": "",
  "dna": "4172012dda480c28e7301ae4d15b44c25045c14d",
  "edition": 6113,
  "date": 1678008913878,
  "attributes": [
    {
      "trait": "BACKGROUND",
      "value": "ORANGE"
    },
    {
      "trait": "BASE",
      "value": "WHALEY LILA"
    },
    {
      "trait": "EYE ACCESSORY",
      "value": "CUTE"
    },
    {
      "trait": "HEADGEAR",
      "value": "YELLOW CAP"
    },
    {
      "trait": "MOUTH ACCESSORY",
      "value": "NONE"
    }
  ],
  "asset_type": "image/png",
  "image": "ipfs://ipfs/QmYSyAWEo9Jv46QhVvzsDmZt7sPCHKE5ChjcHf3MPY7Y1E/images/6113.png"
}