{
  "sip": 16,
  "name": "Stacks Whales #6258",
  "properties": {
    "collection": "Stacks Whales"
  },
  "description": "Whale NFTs on the Stack blockchain are a captivating way to own and display artwork of majestic sea creatures.",
  "size": "10000",
  "price": "1",
  "external_url": "",
  "dna": "69bf027729bdb28e4d74df62852428dd17d77ec3",
  "edition": 6258,
  "date": 1678008686575,
  "attributes": [
    {
      "trait": "BACKGROUND",
      "value": "WHITE"
    },
    {
      "trait": "BASE",
      "value": "WHALEY BLUE"
    },
    {
      "trait": "EYE ACCESSORY",
      "value": "NONE"
    },
    {
      "trait": "HEADGEAR",
      "value": "BEANIE"
    },
    {
      "trait": "MOUTH ACCESSORY",
      "value": "NONE"
    }
  ],
  "asset_type": "image/png",
  "image": "ipfs://ipfs/QmYSyAWEo9Jv46QhVvzsDmZt7sPCHKE5ChjcHf3MPY7Y1E/images/6258.png"
}