{
  "sip": 16,
  "name": "Stacks Whales #6280",
  "properties": {
    "collection": "Stacks Whales"
  },
  "description": "Whale NFTs on the Stack blockchain are a captivating way to own and display artwork of majestic sea creatures.",
  "size": "10000",
  "price": "1",
  "external_url": "",
  "dna": "47f674f7a1ff777b453918fd8888d31812f200e6",
  "edition": 6280,
  "date": 1678008503449,
  "attributes": [
    {
      "trait": "BACKGROUND",
      "value": "RED"
    },
    {
      "trait": "BASE",
      "value": "WHALEY GREEN"
    },
    {
      "trait": "EYE ACCESSORY",
      "value": "CUTE"
    },
    {
      "trait": "HEADGEAR",
      "value": "BEANIE"
    },
    {
      "trait": "MOUTH ACCESSORY",
      "value": "NONE"
    }
  ],
  "asset_type": "image/png",
  "image": "ipfs://ipfs/QmYSyAWEo9Jv46QhVvzsDmZt7sPCHKE5ChjcHf3MPY7Y1E/images/6280.png"
}