{
  "sip": 16,
  "name": "Stacks Whales #6481",
  "properties": {
    "collection": "Stacks Whales"
  },
  "description": "Whale NFTs on the Stack blockchain are a captivating way to own and display artwork of majestic sea creatures.",
  "size": "10000",
  "price": "1",
  "external_url": "",
  "dna": "95eb7a30d279bd708a11c56c2e3ff50dea34a41c",
  "edition": 6481,
  "date": 1678009136178,
  "attributes": [
    {
      "trait": "BACKGROUND",
      "value": "CYAN"
    },
    {
      "trait": "BASE",
      "value": "WHALEY GREEN"
    },
    {
      "trait": "EYE ACCESSORY",
      "value": "CUTE"
    },
    {
      "trait": "HEADGEAR",
      "value": "GREEN CAP"
    },
    {
      "trait": "MOUTH ACCESSORY",
      "value": "PIPE"
    }
  ],
  "asset_type": "image/png",
  "image": "ipfs://ipfs/QmYSyAWEo9Jv46QhVvzsDmZt7sPCHKE5ChjcHf3MPY7Y1E/images/6481.png"
}