{
  "sip": 16,
  "name": "Stacks Whales #658",
  "properties": {
    "collection": "Stacks Whales"
  },
  "description": "Whale NFTs on the Stack blockchain are a captivating way to own and display artwork of majestic sea creatures.",
  "size": "10000",
  "price": "1",
  "external_url": "",
  "dna": "a5b8987101a8adb8072f53f9df5ae154b47aefce",
  "edition": 658,
  "date": 1678008772762,
  "attributes": [
    {
      "trait": "BACKGROUND",
      "value": "BLUE"
    },
    {
      "trait": "BASE",
      "value": "WHALEY BLUE"
    },
    {
      "trait": "EYE ACCESSORY",
      "value": "NONE"
    },
    {
      "trait": "HEADGEAR",
      "value": "DREAMS"
    },
    {
      "trait": "MOUTH ACCESSORY",
      "value": "NONE"
    }
  ],
  "asset_type": "image/png",
  "image": "ipfs://ipfs/QmYSyAWEo9Jv46QhVvzsDmZt7sPCHKE5ChjcHf3MPY7Y1E/images/658.png"
}