{
  "sip": 16,
  "name": "Stacks Whales #6807",
  "properties": {
    "collection": "Stacks Whales"
  },
  "description": "Whale NFTs on the Stack blockchain are a captivating way to own and display artwork of majestic sea creatures.",
  "size": "10000",
  "price": "1",
  "external_url": "",
  "dna": "6df9ea16612e031c7781e995b45d6cd7b5138705",
  "edition": 6807,
  "date": 1678008873705,
  "attributes": [
    {
      "trait": "BACKGROUND",
      "value": "PURPLE"
    },
    {
      "trait": "BASE",
      "value": "WHALEY BLACK"
    },
    {
      "trait": "EYE ACCESSORY",
      "value": "BLUE EYE SHADOW"
    },
    {
      "trait": "HEADGEAR",
      "value": "PURPLE CAP"
    },
    {
      "trait": "MOUTH ACCESSORY",
      "value": "NONE"
    }
  ],
  "asset_type": "image/png",
  "image": "ipfs://ipfs/QmYSyAWEo9Jv46QhVvzsDmZt7sPCHKE5ChjcHf3MPY7Y1E/images/6807.png"
}