{
  "sip": 16,
  "name": "Stacks Whales #8230",
  "properties": {
    "collection": "Stacks Whales"
  },
  "description": "Whale NFTs on the Stack blockchain are a captivating way to own and display artwork of majestic sea creatures.",
  "size": "10000",
  "price": "1",
  "external_url": "",
  "dna": "69bfab50cb7380d40c7eca0feabdd44b722ea5bf",
  "edition": 8230,
  "date": 1678008958244,
  "attributes": [
    {
      "trait": "BACKGROUND",
      "value": "PINK"
    },
    {
      "trait": "BASE",
      "value": "WHALEY BLACK"
    },
    {
      "trait": "EYE ACCESSORY",
      "value": "CLOWN EYE"
    },
    {
      "trait": "HEADGEAR",
      "value": "AMIGO"
    },
    {
      "trait": "MOUTH ACCESSORY",
      "value": "NONE"
    }
  ],
  "asset_type": "image/png",
  "image": "ipfs://ipfs/QmYSyAWEo9Jv46QhVvzsDmZt7sPCHKE5ChjcHf3MPY7Y1E/images/8230.png"
}