{
  "sip": 16,
  "name": "Stacks Whales #8485",
  "properties": {
    "collection": "Stacks Whales"
  },
  "description": "Whale NFTs on the Stack blockchain are a captivating way to own and display artwork of majestic sea creatures.",
  "size": "10000",
  "price": "1",
  "external_url": "",
  "dna": "821592aba854bb1250ac8aeb0dda15f8f384b379",
  "edition": 8485,
  "date": 1678009009981,
  "attributes": [
    {
      "trait": "BACKGROUND",
      "value": "RED"
    },
    {
      "trait": "BASE",
      "value": "WHALEY ORANGE"
    },
    {
      "trait": "EYE ACCESSORY",
      "value": "BLUE EYE SHADOW"
    },
    {
      "trait": "HEADGEAR",
      "value": "RED CAP"
    },
    {
      "trait": "MOUTH ACCESSORY",
      "value": "NONE"
    }
  ],
  "asset_type": "image/png",
  "image": "ipfs://ipfs/QmYSyAWEo9Jv46QhVvzsDmZt7sPCHKE5ChjcHf3MPY7Y1E/images/8485.png"
}