{
  "sip": 16,
  "name": "Stacks Whales #8723",
  "properties": {
    "collection": "Stacks Whales"
  },
  "description": "Whale NFTs on the Stack blockchain are a captivating way to own and display artwork of majestic sea creatures.",
  "size": "10000",
  "price": "1",
  "external_url": "",
  "dna": "815bb45590e120057db7e6f58d939d7705235d66",
  "edition": 8723,
  "date": 1678009169373,
  "attributes": [
    {
      "trait": "BACKGROUND",
      "value": "PEACH"
    },
    {
      "trait": "BASE",
      "value": "WHALEY GREEN"
    },
    {
      "trait": "EYE ACCESSORY",
      "value": "ANGRY"
    },
    {
      "trait": "HEADGEAR",
      "value": "PURPLE BEATS"
    },
    {
      "trait": "MOUTH ACCESSORY",
      "value": "NONE"
    }
  ],
  "asset_type": "image/png",
  "image": "ipfs://ipfs/QmYSyAWEo9Jv46QhVvzsDmZt7sPCHKE5ChjcHf3MPY7Y1E/images/8723.png"
}