{
  "sip": 16,
  "name": "Stacks Whales #8928",
  "properties": {
    "collection": "Stacks Whales"
  },
  "description": "Whale NFTs on the Stack blockchain are a captivating way to own and display artwork of majestic sea creatures.",
  "size": "10000",
  "price": "1",
  "external_url": "",
  "dna": "94b481d83b6474b30eaf93a4ff470feef224c7f2",
  "edition": 8928,
  "date": 1678009126830,
  "attributes": [
    {
      "trait": "BACKGROUND",
      "value": "BLUE"
    },
    {
      "trait": "BASE",
      "value": "WHALEY BLUE"
    },
    {
      "trait": "EYE ACCESSORY",
      "value": "BLUE EYE SHADOW"
    },
    {
      "trait": "HEADGEAR",
      "value": "FEDORA PURPLE"
    },
    {
      "trait": "MOUTH ACCESSORY",
      "value": "NONE"
    }
  ],
  "asset_type": "image/png",
  "image": "ipfs://ipfs/QmYSyAWEo9Jv46QhVvzsDmZt7sPCHKE5ChjcHf3MPY7Y1E/images/8928.png"
}