{
  "sip": 16,
  "name": "Stacks Whales #9732",
  "properties": {
    "collection": "Stacks Whales"
  },
  "description": "Whale NFTs on the Stack blockchain are a captivating way to own and display artwork of majestic sea creatures.",
  "size": "10000",
  "price": "1",
  "external_url": "",
  "dna": "a37572e820e0dd072b74cff53c68de7dbd11c92a",
  "edition": 9732,
  "date": 1678008772128,
  "attributes": [
    {
      "trait": "BACKGROUND",
      "value": "BLUE"
    },
    {
      "trait": "BASE",
      "value": "WHALEY VIOLET"
    },
    {
      "trait": "EYE ACCESSORY",
      "value": "GREEN EYE SHADOW"
    },
    {
      "trait": "HEADGEAR",
      "value": "VIKING HAT"
    },
    {
      "trait": "MOUTH ACCESSORY",
      "value": "NONE"
    }
  ],
  "asset_type": "image/png",
  "image": "ipfs://ipfs/QmYSyAWEo9Jv46QhVvzsDmZt7sPCHKE5ChjcHf3MPY7Y1E/images/9732.png"
}