{
  "sip": 16,
  "name": "Stacks Whales #9737",
  "properties": {
    "collection": "Stacks Whales"
  },
  "description": "Whale NFTs on the Stack blockchain are a captivating way to own and display artwork of majestic sea creatures.",
  "size": "10000",
  "price": "1",
  "external_url": "",
  "dna": "eaf8535c89db673d870a7f7d42896c730907a5e9",
  "edition": 9737,
  "date": 1678008959003,
  "attributes": [
    {
      "trait": "BACKGROUND",
      "value": "YELLOW"
    },
    {
      "trait": "BASE",
      "value": "WHALEY BLACK"
    },
    {
      "trait": "EYE ACCESSORY",
      "value": "NONE"
    },
    {
      "trait": "HEADGEAR",
      "value": "RED HEADBAND"
    },
    {
      "trait": "MOUTH ACCESSORY",
      "value": "PIPE"
    }
  ],
  "asset_type": "image/png",
  "image": "ipfs://ipfs/QmYSyAWEo9Jv46QhVvzsDmZt7sPCHKE5ChjcHf3MPY7Y1E/images/9737.png"
}